LICENSE
README.md
setup.py
capsa/__init__.py
capsa/base_wrapper.py
capsa/risk_tensor.py
capsa.egg-info/PKG-INFO
capsa.egg-info/SOURCES.txt
capsa.egg-info/dependency_links.txt
capsa.egg-info/not-zip-safe
capsa.egg-info/top_level.txt
capsa/aleatoric/__init__.py
capsa/aleatoric/mve.py
capsa/bias/__init__.py
capsa/bias/histogram.py
capsa/bias/histogramvae.py
capsa/epistemic/__init__.py
capsa/epistemic/dropout.py
capsa/epistemic/ensemble.py
capsa/epistemic/vae.py
capsa/utils/__init__.py
capsa/utils/utils.py
test/test_bias.py
test/test_dropout.py
test/test_ensemble.py
test/test_exceptions.py
test/test_mve.py
test/test_risk_tensor.py
test/test_risk_tensor_nn.py
test/test_vae.py