Metadata-Version: 2.1
Name: capsa
Version: 0.1.5
Summary: A data- and model-agnostic neural network wrapper for risk-aware decision making
Home-page: https://github.com/themis-ai/capsa
Download-URL: https://github.com/themis-ai/capsa/archive/refs/tags/0.1.5.tar.gz
Author: Themis AI
Author-email: info@themisai.io
License: GNU Affero General Public License v3.0
Keywords: capsa
Classifier: Development Status :: 2 - Pre-Alpha
Classifier: Intended Audience :: Developers
Classifier: Natural Language :: English
Classifier: Programming Language :: Python :: 3
Classifier: Programming Language :: Python :: 3.7
Classifier: Programming Language :: Python :: 3.8
Classifier: Programming Language :: Python :: 3.9
Classifier: Programming Language :: Python :: 3.10
Requires-Python: >=3.5
License-File: LICENSE
